TinyTinyDebugger/LICENSE
TinyTinyDebugger/README.MD
TinyTinyDebugger/__init__.py
TinyTinyDebugger/requirements.txt
TinyTinyDebugger/thirdparty.json
TinyTinyDebugger-0.14.dist-info/LICENSE.rst
TinyTinyDebugger-0.14.dist-info/METADATA
TinyTinyDebugger-0.14.dist-info/WHEEL
TinyTinyDebugger-0.14.dist-info/top_level.txt
TinyTinyDebugger-0.14.dist-info/RECORD
