Metadata-Version: 2.1
Name: TinyTinyDebugger
Version: 0.14
Summary: Simple debugger for small scripts, shows the line being executed, local vars ...
Home-page: https://github.com/hansalemaos/TinyTinyDebugger
Author: Johannes Fischer
Author-email: <aulasparticularesdealemaosp@gmail.com>
License: MIT
Keywords: debugger,debugging
Classifier: Development Status :: 4 - Beta
Classifier: Programming Language :: Python :: 3 :: Only
Classifier: Programming Language :: Python :: 3.9
Classifier: Topic :: Scientific/Engineering :: Visualization
Classifier: Topic :: Software Development :: Libraries :: Python Modules
Classifier: Topic :: Text Editors :: Text Processing
Classifier: Topic :: Text Processing :: General
Classifier: Topic :: Text Processing :: Indexing
Classifier: Topic :: Text Processing :: Filters
Classifier: Topic :: Utilities
License-File: LICENSE.rst
Requires-Dist: copy-functions-and-more
Requires-Dist: cprinter
Requires-Dist: files-folders-with-timestamp
Requires-Dist: sleepchunk
Requires-Dist: tolerant-isinstance
Requires-Dist: windows-filepath
